coldwallet/__init__.py
coldwallet/aes.py
coldwallet/bitcoin.py
coldwallet/command_line.py
coldwallet/crypto.py
coldwallet/encoding.py
coldwallet/keyentry.py
coldwallet/reader.py
coldwallet-0.0.13.dist-info/DESCRIPTION.rst
coldwallet-0.0.13.dist-info/METADATA
coldwallet-0.0.13.dist-info/RECORD
coldwallet-0.0.13.dist-info/WHEEL
coldwallet-0.0.13.dist-info/entry_points.txt
coldwallet-0.0.13.dist-info/metadata.json
coldwallet-0.0.13.dist-info/top_level.txt
